{
  "display": {
    "icon": {
      "item": "markscoins:usa_anthem"
    },
    "title": {
      "translate": "advancements.usa_adv.title"
    },
    "description": {
      "translate": "advancements.usa_adv.descr"
    },
    "frame": "task",
    "show_toast": true,
    "announce_to_chat": true,
    "hidden": false
  },
  "criteria": {
    "usa_adv": {
      "trigger": "minecraft:inventory_changed",
      "conditions": {
        "items": [
          {
            "items": [
              "markscoins:usa_anthem"
            ],
            "count": {
              "min": 1,
              "max": 1
            }
          }
        ]
      }
    }
  },
  "rewards": {
    "experience": 13
  },
  "parent": "markscoins:wood_adv"
}